amn/__init__.py
amn/core/__init__.py
amn/core/constraints.py
amn/core/decoder.py
amn/core/objectives.py
amn/core/optimizer.py
amn/core/utils.py
amn/problems/__init__.py
amn/problems/allocation.py
amn/problems/routing.py
amn/problems/scheduling.py
artificial_muscle_network-2.0.0.dist-info/licenses/LICENSE
artificial_muscle_network-2.0.0.dist-info/METADATA
artificial_muscle_network-2.0.0.dist-info/WHEEL
artificial_muscle_network-2.0.0.dist-info/top_level.txt
artificial_muscle_network-2.0.0.dist-info/RECORD
