Metadata-Version: 2.4
Name: artificial-muscle-network
Version: 2.0.0
Summary: Artificial Muscle Network: physics-inspired optimization for scheduling, routing, and allocation
Author: AMN Maintainers
License: MIT
Project-URL: Homepage, https://github.com/eldm-ethanmoore/artificial-muscle-network
Project-URL: Documentation, https://eldm-ethanmoore.github.io/artificial-muscle-network/
Project-URL: Issues, https://github.com/eldm-ethanmoore/artificial-muscle-network/issues
Keywords: optimization,scheduling,routing,allocation,operations research
Classifier: Programming Language :: Python :: 3
Classifier: License :: OSI Approved :: MIT License
Classifier: Operating System :: OS Independent
Requires-Python: >=3.9
License-File: LICENSE
Dynamic: license-file
